MANIFEST.in
README.rst
setup.py
doc/.gitignore
doc/Makefile
doc/api.rst
doc/body_plot.rst
doc/channel_plot.rst
doc/conf.py
doc/defaultargs.rst
doc/getting_started.rst
doc/index.rst
doc/make.bat
doc/manual.rst
doc/plotting.rst
doc/reflectivity.rst
doc/stochastic_avo.rst
doc/url_plot.rst
doc/wavelet.rst
doc/web_framework.rst
doc/_build/doctrees/api.doctree
doc/_build/doctrees/body_plot.doctree
doc/_build/doctrees/channel_plot.doctree
doc/_build/doctrees/defaultargs.doctree
doc/_build/doctrees/environment.pickle
doc/_build/doctrees/getting_started.doctree
doc/_build/doctrees/index.doctree
doc/_build/doctrees/manual.doctree
doc/_build/doctrees/plotting.doctree
doc/_build/doctrees/reflectivity.doctree
doc/_build/doctrees/stochastic_avo.doctree
doc/_build/doctrees/url_plot.doctree
doc/_build/doctrees/wavelet.doctree
doc/_build/doctrees/web_framework.doctree
doc/_build/html/.buildinfo
doc/_build/html/api.html
doc/_build/html/body_plot.html
doc/_build/html/channel_plot.html
doc/_build/html/defaultargs.html
doc/_build/html/genindex.html
doc/_build/html/getting_started.html
doc/_build/html/index.html
doc/_build/html/manual.html
doc/_build/html/objects.inv
doc/_build/html/plotting.html
doc/_build/html/py-modindex.html
doc/_build/html/reflectivity.html
doc/_build/html/search.html
doc/_build/html/searchindex.js
doc/_build/html/stochastic_avo.html
doc/_build/html/url_plot.html
doc/_build/html/wavelet.html
doc/_build/html/web_framework.html
doc/_build/html/_modules/index.html
doc/_build/html/_modules/agilegeo/avo.html
doc/_build/html/_modules/agilegeo/wavelet.html
doc/_build/html/_modules/modelr/modelbuilder.html
doc/_build/html/_modules/modelr/reflectivity.html
doc/_build/html/_modules/modelr/rock_properties.html
doc/_build/html/_modules/modelr/web/server.html
doc/_build/html/_modules/modelr/web/urlargparse.html
doc/_build/html/_modules/modelr/web/util.html
doc/_build/html/_sources/api.txt
doc/_build/html/_sources/body_plot.txt
doc/_build/html/_sources/channel_plot.txt
modelr.egg-info/PKG-INFO
modelr.egg-info/SOURCES.txt
modelr.egg-info/dependency_links.txt
modelr.egg-info/entry_points.txt
modelr.egg-info/requires.txt
modelr.egg-info/top_level.txt
